fall/__init__.py
fall/utils.py
fall/adaptive_learning/__init__.py
fall/adaptive_learning/base.py
fall/adaptive_learning/buffer.py
fall/adaptive_learning/classifier_adaptation.py
fall/adaptive_learning/discrete_segment.py
fall/adaptive_learning/reidentification_schedulers.py
fall/adaptive_learning/test_base_adaptive_learner.py
fall/adaptive_learning/test_base_buffer_adaptive_learner.py
fall/adaptive_learning/test_buffer.py
fall/adaptive_learning/test_classifier_adaptation.py
fall/adaptive_learning/test_discrete_segment_AL.py
fall/adaptive_learning/test_reidentification_schedulers.py
fall/classifiers/__init__.py
fall/concept_representations/__init__.py
fall/concept_representations/base.py
fall/concept_representations/error_rate_representation.py
fall/concept_representations/meta_feature_distributions.py
fall/concept_representations/test_distributions.py
fall/concept_representations/test_representations.py
fall/data/__init__.py
fall/data/datastream.py
fall/data/test_datastream.py
fall/data/test_transition_patterns.py
fall/data/transition_patterns.py
fall/data/utils.py
fall/data/synthetic/gaussian.py
fall/data/synthetic/wind_sim.py
fall/evaluation/context_inference.py
fall/evaluation/monitoring.py
fall/evaluation/utils.py
fall/repository/__init__.py
fall/repository/base.py
fall/repository/comparers.py
fall/repository/test_addition.py
fall/repository/test_comparers.py
fall/repository/test_deletion.py
fall/repository/test_repository.py
fall/repository/test_transition_fsm.py
fall/repository/transition_fsm.py
fall/states/__init__.py
fall/states/base.py
fall/states/test_states.py
fall_ml-0.0.1.dist-info/LICENSE
fall_ml-0.0.1.dist-info/METADATA
fall_ml-0.0.1.dist-info/WHEEL
fall_ml-0.0.1.dist-info/top_level.txt
fall_ml-0.0.1.dist-info/RECORD
