Metadata-Version: 2.1
Name: fall-ml
Version: 0.0.1
Summary: Real-time lifelong machine learning
Author: "Ben Halstead"
Author-email: Ben Halstead <benhalstd@gmail.com>
License: BSD 3-Clause License        
Project-URL: Homepage, https://benhalstead.dev/FALL
Keywords: machine learning,data stream
Classifier: Programming Language :: Python
Classifier: Programming Language :: Python :: 3
Requires-Python: >=3.9
License-File: LICENSE
Requires-Dist: river
Provides-Extra: dev
Requires-Dist: black ; extra == 'dev'
Requires-Dist: flake8 ; extra == 'dev'
Requires-Dist: ipython ; extra == 'dev'
Requires-Dist: matplotlib ; extra == 'dev'
Requires-Dist: pytest ; extra == 'dev'
Requires-Dist: mypy ; extra == 'dev'
Requires-Dist: pylint ; extra == 'dev'
Requires-Dist: networkx ; extra == 'dev'
Provides-Extra: test
Requires-Dist: pytest ; extra == 'test'
